simple_loader/__init__.py
simple_loader-0.1.0.dist-info/licenses/LICENSE
simple_loader-0.1.0.dist-info/METADATA
simple_loader-0.1.0.dist-info/WHEEL
simple_loader-0.1.0.dist-info/top_level.txt
simple_loader-0.1.0.dist-info/RECORD
