Metadata-Version: 2.4
Name: simple-loader
Version: 0.1.0
Summary: A simple loader for .env, .json, and .yaml config files
Author-email: redbean0721 <redbean0721@redbean0721.com>
License: MIT
Requires-Python: >=3.7
License-File: LICENSE
Requires-Dist: python-dotenv
Requires-Dist: pyyaml
Dynamic: license-file
